odoo8_addon_stock_inventory_revaluation-8.0.1.1.0-py2.7-nspkg.pth
odoo_addons/stock_inventory_revaluation/__openerp__.py
odoo_addons/stock_inventory_revaluation/__init__.py
odoo_addons/stock_inventory_revaluation/README.rst
odoo_addons/stock_inventory_revaluation/security/stock_inventory_revaluation_security.xml
odoo_addons/stock_inventory_revaluation/security/ir.model.access.csv
odoo_addons/stock_inventory_revaluation/migrations/8.0.1.1.0/pre-migration.py
odoo_addons/stock_inventory_revaluation/models/product.py
odoo_addons/stock_inventory_revaluation/models/stock_inventory_revaluation.py
odoo_addons/stock_inventory_revaluation/models/__init__.py
odoo_addons/stock_inventory_revaluation/models/account_move.py
odoo_addons/stock_inventory_revaluation/i18n/ja.po
odoo_addons/stock_inventory_revaluation/i18n/nl_NL.po
odoo_addons/stock_inventory_revaluation/i18n/lv.po
odoo_addons/stock_inventory_revaluation/i18n/zh_CN.po
odoo_addons/stock_inventory_revaluation/i18n/nb_NO.po
odoo_addons/stock_inventory_revaluation/i18n/uk.po
odoo_addons/stock_inventory_revaluation/i18n/es_AR.po
odoo_addons/stock_inventory_revaluation/i18n/ko.po
odoo_addons/stock_inventory_revaluation/i18n/tr_TR.po
odoo_addons/stock_inventory_revaluation/i18n/ru.po
odoo_addons/stock_inventory_revaluation/i18n/gl_ES.po
odoo_addons/stock_inventory_revaluation/i18n/pt.po
odoo_addons/stock_inventory_revaluation/i18n/fr_CH.po
odoo_addons/stock_inventory_revaluation/i18n/it.po
odoo_addons/stock_inventory_revaluation/i18n/es_CL.po
odoo_addons/stock_inventory_revaluation/i18n/es.po
odoo_addons/stock_inventory_revaluation/i18n/nl_BE.po
odoo_addons/stock_inventory_revaluation/i18n/fr_FR.po
odoo_addons/stock_inventory_revaluation/i18n/ar.po
odoo_addons/stock_inventory_revaluation/i18n/lt.po
odoo_addons/stock_inventory_revaluation/i18n/vi_VN.po
odoo_addons/stock_inventory_revaluation/i18n/ro.po
odoo_addons/stock_inventory_revaluation/i18n/tr.po
odoo8_addon_stock_inventory_revaluation-8.0.1.1.0.dist-info/top_level.txt
odoo8_addon_stock_inventory_revaluation-8.0.1.1.0.dist-info/WHEEL
odoo8_addon_stock_inventory_revaluation-8.0.1.1.0.dist-info/RECORD
odoo8_addon_stock_inventory_revaluation-8.0.1.1.0.dist-info/metadata.json
odoo8_addon_stock_inventory_revaluation-8.0.1.1.0.dist-info/DESCRIPTION.rst
odoo8_addon_stock_inventory_revaluation-8.0.1.1.0.dist-info/METADATA
odoo8_addon_stock_inventory_revaluation-8.0.1.1.0.dist-info/namespace_packages.txt
