Metadata-Version: 2.0
Name: odoo8-addon-stock-inventory-revaluation
Version: 8.0.1.1.0
Summary: Introduces inventory revaluation as single point to change the valuation of products.
Home-page: http://www.eficent.com
Author: Eficent Business and IT Consulting Services S.L., Odoo Community Association (OCA)
Author-email: support@odoo-community.org
License: AGPL-3
Platform: UNKNOWN
Requires-Dist: odoo (<9.0a,>=8.0a)
Classifier: Programming Language :: Python :: 2.7
Classifier: Framework :: Odoo
Classifier: License :: OSI Approved :: GNU Affero General Public License v3
